<?xml version="1.0" encoding="utf-8" ?>
<c2layout>
    <name>Screen</name>
    <sid>361370174910559</sid>
    <event-sheet>Event sheet 2</event-sheet>
    <size>
        <width>1280</width>
        <height>720</height>
    </size>
    <margins>
        <horizontal>500</horizontal>
        <vertical>500</vertical>
    </margins>
    <unbounded-scrolling>0</unbounded-scrolling>
    <layers>
        <layer name="Layer 0" sid="512974215535982">
            <initially-visible>1</initially-visible>
            <background-color>255,255,255</background-color>
            <transparent>0</transparent>
            <parallax>
                <x>1</x>
                <y>1</y>
            </parallax>
            <zoom-rate>1</zoom-rate>
            <opacity>1</opacity>
            <force-own-texture>0</force-own-texture>
            <global>0</global>
            <use-render-cells>0</use-render-cells>
            <blend-mode>0</blend-mode>
            <effect-fallback>0</effect-fallback>
            <instances>
                <instance type="Sprite" uid="13">
                    <properties>
                        <initial-visibility>Visible</initial-visibility>
                        <initial-animation>Default</initial-animation>
                        <initial-frame>0</initial-frame>
                        <collisions>Enabled</collisions>
                    </properties>
                    <blend-mode>0</blend-mode>
                    <effect-fallback>0</effect-fallback>
                    <world>
                        <x>659</x>
                        <y>458</y>
                        <z>0</z>
                        <width>1449</width>
                        <height>993</height>
                        <depth>0</depth>
                        <hotspotX>0.5</hotspotX>
                        <hotspotY>0.5</hotspotY>
                        <angle>0</angle>
                        <opacity>1</opacity>
                    </world>
                </instance>
                <instance type="run" uid="14">
                    <properties>
                        <initial-visibility>Visible</initial-visibility>
                        <initial-animation>Default</initial-animation>
                        <initial-frame>0</initial-frame>
                        <collisions>Enabled</collisions>
                    </properties>
                    <behavior-instances>
                        <behavior-instance type="Platform">
                            <properties>
                                <max-speed>330</max-speed>
                                <acceleration>1500</acceleration>
                                <deceleration>1500</deceleration>
                                <jump-strength>800</jump-strength>
                                <gravity>1500</gravity>
                                <max-fall-speed>1000</max-fall-speed>
                                <double-jump>Disabled</double-jump>
                                <jump-sustain>0</jump-sustain>
                                <default-controls>Yes</default-controls>
                                <initial-state>Enabled</initial-state>
                            </properties>
                        </behavior-instance>
                    </behavior-instances>
                    <blend-mode>0</blend-mode>
                    <effect-fallback>0</effect-fallback>
                    <world>
                        <x>163</x>
                        <y>572</y>
                        <z>0</z>
                        <width>76.874984741</width>
                        <height>71.915313721</height>
                        <depth>0</depth>
                        <hotspotX>0.470930219</hotspotX>
                        <hotspotY>0.529069781</hotspotY>
                        <angle>0</angle>
                        <opacity>1</opacity>
                    </world>
                </instance>
                <instance type="Sprite3" uid="15">
                    <properties>
                        <initial-visibility>Visible</initial-visibility>
                        <initial-animation>Default</initial-animation>
                        <initial-frame>0</initial-frame>
                        <collisions>Enabled</collisions>
                    </properties>
                    <blend-mode>0</blend-mode>
                    <effect-fallback>0</effect-fallback>
                    <world>
                        <x>735</x>
                        <y>545</y>
                        <z>0</z>
                        <width>53</width>
                        <height>99</height>
                        <depth>0</depth>
                        <hotspotX>0.445652187</hotspotX>
                        <hotspotY>0.28873238</hotspotY>
                        <angle>0</angle>
                        <opacity>1</opacity>
                    </world>
                </instance>
                <instance type="TiledBackground" uid="16">
                    <properties>
                        <initial-visibility>Visible</initial-visibility>
                        <hotspot>Top-left</hotspot>
                    </properties>
                    <behavior-instances>
                        <behavior-instance type="Solid">
                            <properties>
                                <initial-state>Enabled</initial-state>
                            </properties>
                        </behavior-instance>
                        <behavior-instance type="Wrap">
                            <properties>
                                <wrap-to>Layout</wrap-to>
                            </properties>
                        </behavior-instance>
                    </behavior-instances>
                    <blend-mode>0</blend-mode>
                    <effect-fallback>0</effect-fallback>
                    <world>
                        <x>-1358</x>
                        <y>612</y>
                        <z>0</z>
                        <width>10000</width>
                        <height>160</height>
                        <depth>0</depth>
                        <hotspotX>0</hotspotX>
                        <hotspotY>0</hotspotY>
                        <angle>0</angle>
                        <opacity>1</opacity>
                    </world>
                </instance>
                <instance type="Sprite4" uid="17">
                    <properties>
                        <initial-visibility>Visible</initial-visibility>
                        <initial-animation>Default</initial-animation>
                        <initial-frame>0</initial-frame>
                        <collisions>Enabled</collisions>
                    </properties>
                    <blend-mode>0</blend-mode>
                    <effect-fallback>0</effect-fallback>
                    <world>
                        <x>721</x>
                        <y>132</y>
                        <z>0</z>
                        <width>214.243026733</width>
                        <height>108.630264282</height>
                        <depth>0</depth>
                        <hotspotX>0.5</hotspotX>
                        <hotspotY>0.569444418</hotspotY>
                        <angle>0</angle>
                        <opacity>1</opacity>
                    </world>
                </instance>
                <instance type="Sprite5" uid="18">
                    <properties>
                        <initial-visibility>Visible</initial-visibility>
                        <initial-animation>Default</initial-animation>
                        <initial-frame>0</initial-frame>
                        <collisions>Enabled</collisions>
                    </properties>
                    <blend-mode>0</blend-mode>
                    <effect-fallback>0</effect-fallback>
                    <world>
                        <x>1120</x>
                        <y>267</y>
                        <z>0</z>
                        <width>142</width>
                        <height>72</height>
                        <depth>0</depth>
                        <hotspotX>0.5</hotspotX>
                        <hotspotY>0.569444418</hotspotY>
                        <angle>0</angle>
                        <opacity>1</opacity>
                    </world>
                </instance>
                <instance type="Sprite6" uid="19">
                    <properties>
                        <initial-visibility>Visible</initial-visibility>
                        <initial-animation>Default</initial-animation>
                        <initial-frame>0</initial-frame>
                        <collisions>Enabled</collisions>
                    </properties>
                    <blend-mode>0</blend-mode>
                    <effect-fallback>0</effect-fallback>
                    <world>
                        <x>934</x>
                        <y>451</y>
                        <z>0</z>
                        <width>79</width>
                        <height>65</height>
                        <depth>0</depth>
                        <hotspotX>0.506329119</hotspotX>
                        <hotspotY>0.507692337</hotspotY>
                        <angle>0</angle>
                        <opacity>1</opacity>
                    </world>
                </instance>
                <instance type="Sprite7" uid="20">
                    <properties>
                        <initial-visibility>Visible</initial-visibility>
                        <initial-animation>Default</initial-animation>
                        <initial-frame>0</initial-frame>
                        <collisions>Enabled</collisions>
                    </properties>
                    <blend-mode>0</blend-mode>
                    <effect-fallback>0</effect-fallback>
                    <world>
                        <x>677</x>
                        <y>299</y>
                        <z>0</z>
                        <width>130.875320435</width>
                        <height>132.943328857</height>
                        <depth>0</depth>
                        <hotspotX>0.501128674</hotspotX>
                        <hotspotY>0.5</hotspotY>
                        <angle>0</angle>
                        <opacity>1</opacity>
                    </world>
                </instance>
                <instance type="Text" uid="23">
                    <properties>
                        <text>0</text>
                        <initial-visibility>Visible</initial-visibility>
                        <font>Arial,-64,400,0</font>
                        <color>0,0,0</color>
                        <horizontal-alignment>Left</horizontal-alignment>
                        <vertical-alignment>Center</vertical-alignment>
                        <hotspot>Top-left</hotspot>
                        <wrapping>Word</wrapping>
                        <line-height>0</line-height>
                    </properties>
                    <blend-mode>0</blend-mode>
                    <effect-fallback>0</effect-fallback>
                    <world>
                        <x>520</x>
                        <y>196</y>
                        <z>0</z>
                        <width>300</width>
                        <height>99</height>
                        <depth>0</depth>
                        <hotspotX>0</hotspotX>
                        <hotspotY>0</hotspotY>
                        <angle>0</angle>
                        <opacity>1</opacity>
                    </world>
                </instance>
                <instance type="Text2" uid="24">
                    <properties>
                        <text>Score :</text>
                        <initial-visibility>Visible</initial-visibility>
                        <font>Arial,-64,400,0</font>
                        <color>0,0,0</color>
                        <horizontal-alignment>Left</horizontal-alignment>
                        <vertical-alignment>Center</vertical-alignment>
                        <hotspot>Top-left</hotspot>
                        <wrapping>Word</wrapping>
                        <line-height>0</line-height>
                    </properties>
                    <blend-mode>0</blend-mode>
                    <effect-fallback>0</effect-fallback>
                    <world>
                        <x>305</x>
                        <y>188</y>
                        <z>0</z>
                        <width>309</width>
                        <height>108</height>
                        <depth>0</depth>
                        <hotspotX>0</hotspotX>
                        <hotspotY>0</hotspotY>
                        <angle>0</angle>
                        <opacity>1</opacity>
                    </world>
                </instance>
                <instance type="Text3" uid="26">
                    <properties>
                        <text>High Score :</text>
                        <initial-visibility>Invisible</initial-visibility>
                        <font>Arial,-64,400,0</font>
                        <color>0,0,0</color>
                        <horizontal-alignment>Left</horizontal-alignment>
                        <vertical-alignment>Center</vertical-alignment>
                        <hotspot>Top-left</hotspot>
                        <wrapping>Word</wrapping>
                        <line-height>0</line-height>
                    </properties>
                    <blend-mode>0</blend-mode>
                    <effect-fallback>0</effect-fallback>
                    <world>
                        <x>155</x>
                        <y>255</y>
                        <z>0</z>
                        <width>441</width>
                        <height>139</height>
                        <depth>0</depth>
                        <hotspotX>0</hotspotX>
                        <hotspotY>0</hotspotY>
                        <angle>0</angle>
                        <opacity>1</opacity>
                    </world>
                </instance>
                <instance type="record1" uid="27">
                    <properties>
                        <text>0</text>
                        <initial-visibility>Invisible</initial-visibility>
                        <font>Arial,-64,400,0</font>
                        <color>0,0,0</color>
                        <horizontal-alignment>Left</horizontal-alignment>
                        <vertical-alignment>Center</vertical-alignment>
                        <hotspot>Top-left</hotspot>
                        <wrapping>Word</wrapping>
                        <line-height>0</line-height>
                    </properties>
                    <blend-mode>0</blend-mode>
                    <effect-fallback>0</effect-fallback>
                    <world>
                        <x>518</x>
                        <y>258</y>
                        <z>0</z>
                        <width>138</width>
                        <height>139</height>
                        <depth>0</depth>
                        <hotspotX>0</hotspotX>
                        <hotspotY>0</hotspotY>
                        <angle>0</angle>
                        <opacity>1</opacity>
                    </world>
                </instance>
                <instance type="Sprite8" uid="28">
                    <properties>
                        <initial-visibility>Visible</initial-visibility>
                        <initial-animation>Default</initial-animation>
                        <initial-frame>0</initial-frame>
                        <collisions>Enabled</collisions>
                    </properties>
                    <blend-mode>0</blend-mode>
                    <effect-fallback>0</effect-fallback>
                    <world>
                        <x>671</x>
                        <y>417</y>
                        <z>0</z>
                        <width>94.892791748</width>
                        <height>94.8438797</height>
                        <depth>0</depth>
                        <hotspotX>0.5</hotspotX>
                        <hotspotY>0.499742121</hotspotY>
                        <angle>0</angle>
                        <opacity>1</opacity>
                    </world>
                </instance>
                <instance type="Sprite9" uid="29">
                    <properties>
                        <initial-visibility>Invisible</initial-visibility>
                        <initial-animation>Default</initial-animation>
                        <initial-frame>0</initial-frame>
                        <collisions>Enabled</collisions>
                    </properties>
                    <blend-mode>0</blend-mode>
                    <effect-fallback>0</effect-fallback>
                    <world>
                        <x>374</x>
                        <y>246</y>
                        <z>0</z>
                        <width>408.794311523</width>
                        <height>325.757965088</height>
                        <depth>0</depth>
                        <hotspotX>0.520833313</hotspotX>
                        <hotspotY>0.519607842</hotspotY>
                        <angle>0</angle>
                        <opacity>1</opacity>
                    </world>
                </instance>
            </instances>
            <effects />
        </layer>
    </layers>
    <nonworld-instances />
    <effects />
</c2layout>
